azure/mgmt/defendereasm/__init__.py
azure/mgmt/defendereasm/_configuration.py
azure/mgmt/defendereasm/_easm_mgmt_client.py
azure/mgmt/defendereasm/_patch.py
azure/mgmt/defendereasm/_serialization.py
azure/mgmt/defendereasm/_vendor.py
azure/mgmt/defendereasm/_version.py
azure/mgmt/defendereasm/py.typed
azure/mgmt/defendereasm/aio/__init__.py
azure/mgmt/defendereasm/aio/_configuration.py
azure/mgmt/defendereasm/aio/_easm_mgmt_client.py
azure/mgmt/defendereasm/aio/_patch.py
azure/mgmt/defendereasm/aio/operations/__init__.py
azure/mgmt/defendereasm/aio/operations/_labels_operations.py
azure/mgmt/defendereasm/aio/operations/_operations.py
azure/mgmt/defendereasm/aio/operations/_patch.py
azure/mgmt/defendereasm/aio/operations/_workspaces_operations.py
azure/mgmt/defendereasm/models/__init__.py
azure/mgmt/defendereasm/models/_easm_mgmt_client_enums.py
azure/mgmt/defendereasm/models/_models_py3.py
azure/mgmt/defendereasm/models/_patch.py
azure/mgmt/defendereasm/operations/__init__.py
azure/mgmt/defendereasm/operations/_labels_operations.py
azure/mgmt/defendereasm/operations/_operations.py
azure/mgmt/defendereasm/operations/_patch.py
azure/mgmt/defendereasm/operations/_workspaces_operations.py
azure_mgmt_defendereasm-1.0.0b1.dist-info/LICENSE
azure_mgmt_defendereasm-1.0.0b1.dist-info/METADATA
azure_mgmt_defendereasm-1.0.0b1.dist-info/WHEEL
azure_mgmt_defendereasm-1.0.0b1.dist-info/top_level.txt
azure_mgmt_defendereasm-1.0.0b1.dist-info/RECORD
